suxarray/__init__.py
suxarray/cli.py
suxarray/suxarray.py
suxarray/util_vtk.py
suxarray-0.1.3.dist-info/AUTHORS.rst
suxarray-0.1.3.dist-info/LICENSE
suxarray-0.1.3.dist-info/METADATA
suxarray-0.1.3.dist-info/WHEEL
suxarray-0.1.3.dist-info/entry_points.txt
suxarray-0.1.3.dist-info/top_level.txt
suxarray-0.1.3.dist-info/RECORD
