Metadata-Version: 2.1
Name: suxarray
Version: 0.1.3
Summary: suxarray is an extension of uxarray for SCHISM.
Home-page: https://github.com/cadwrdeltamodeling/suxarray
Author: California Department of Water Resources
Author-email: knam@water.ca.gov
License: MIT license
Keywords: suxarray
Classifier: Development Status :: 2 - Pre-Alpha
Classifier: Intended Audience :: Developers
Classifier: License :: OSI Approved :: MIT License
Classifier: Natural Language :: English
Classifier: Programming Language :: Python :: 3
Classifier: Programming Language :: Python :: 3.8
Classifier: Programming Language :: Python :: 3.9
Classifier: Programming Language :: Python :: 3.10
Requires-Python: >=3.8,<3.11
License-File: LICENSE
License-File: AUTHORS.rst
Requires-Dist: uxarray (>=2023.4.1)
Requires-Dist: netcdf4
Requires-Dist: shapely (>=2.0)
Requires-Dist: Click (>=7.0)
Provides-Extra: vtk
Requires-Dist: vtk ; extra == 'vtk'
